src/vbox/__init__.py
src/vbox.egg-info/PKG-INFO
src/vbox.egg-info/SOURCES.txt
src/vbox.egg-info/dependency_links.txt
src/vbox.egg-info/top_level.txt
src/vbox/api/__init__.py
src/vbox/api/base.py
src/vbox/api/display.py
src/vbox/api/general.py
src/vbox/api/storage.py
src/vbox/api/system.py
src/vbox/api/vm.py
src/vbox/cli/__init__.py
src/vbox/cli/base.py
src/vbox/cli/chgCmds.py
src/vbox/cli/cliInterface.py
src/vbox/cli/infoCmds.py
src/vbox/cli/list.py
src/vbox/cli/popen.py
src/vbox/cli/subCmd.py
src/vbox/cli/util.py
src/vbox/cli/vboxManage.py
src/vbox/pyVb/__init__.py
src/vbox/pyVb/base.py
src/vbox/pyVb/info.py
src/vbox/pyVb/virtualbox.py
src/vbox/pyVb/disks/__init__.py
src/vbox/pyVb/disks/base.py
src/vbox/pyVb/disks/dvd/__init__.py
src/vbox/pyVb/disks/dvd/dvd.py
src/vbox/pyVb/disks/dvd/library.py
src/vbox/pyVb/disks/floppy/__init__.py
src/vbox/pyVb/disks/floppy/floppy.py
src/vbox/pyVb/disks/floppy/library.py
src/vbox/pyVb/disks/hdd/__init__.py
src/vbox/pyVb/disks/hdd/hdd.py
src/vbox/pyVb/disks/hdd/library.py
src/vbox/pyVb/network/__init__.py
src/vbox/pyVb/network/base.py
src/vbox/pyVb/network/interface.py
src/vbox/pyVb/network/library.py
src/vbox/pyVb/network/dhcpServers/__init__.py
src/vbox/pyVb/network/dhcpServers/library.py
src/vbox/pyVb/network/dhcpServers/server.py
src/vbox/pyVb/util/__init__.py
src/vbox/pyVb/util/boundProperty.py
src/vbox/pyVb/util/cbProps.py
src/vbox/pyVb/util/infoed.py
src/vbox/pyVb/util/props.py
src/vbox/pyVb/vm/__init__.py
src/vbox/pyVb/vm/base.py
src/vbox/pyVb/vm/library.py
src/vbox/pyVb/vm/nic.py
src/vbox/pyVb/vm/state.py
src/vbox/pyVb/vm/storageController.py
src/vbox/pyVb/vm/util.py
src/vbox/pyVb/vm/vm.py