Metadata-Version: 1.1
Name: vbox
Version: 0.2.5
Summary: VirtualBox CLI bindings
Home-page: https://github.com/VRGhost/vbox
Author: Ilja Orlovs
Author-email: ilja@tells.so
License: UNKNOWN
Platform: UNKNOWN
Classifier: Development Status :: 3 - Alpha
Classifier: Environment :: Console
Classifier: Intended Audience :: Developers
Classifier: License :: OSI Approved :: BSD License
Classifier: Operating System :: OS Independent
Classifier: Programming Language :: Python
